Metadata-Version: 1.0
Name: test-gaussian-distributions
Version: 0.1
Summary: Kamal lamichhane test Gaussian distributions
Home-page: UNKNOWN
Author: Kamal Lamichane
Author-email: Kamal.Lamichane@leddartech.com
License: UNKNOWN
Platform: UNKNOWN
